{
	"amiibo": {
		"amiiboSeries": "Splatoon",
		"character": "Inkling",
		"name": "Inkling Girl",
		"gameSeries": "Splatoon",
		"image": "https://raw.githubusercontent.com/N3evin/AmiiboAPI/master/images/icon_08000100-003e0402.png",
		"tail": "003e0402"
	},
	"next": "01c10502.html",
	"prev": "039cff02.html",
	"list": {
		"00080002": "Villager",
		"00150002": "Bowser Jr.",
		"002f0002": "Duck Hunt",
		"009f0502": "Henry",
		"00ed0502": "Ruby",
		"014a0502": "Gaston",
		"017c0502": "Pave",
		"01910502": "Erik",
		"028f0e02": "Donkey Kong - Golf",
		"index": "Sandy"
	}
}
