{
	"amiibo": {
		"amiiboSeries": "Animal Crossing",
		"character": "Bluebear",
		"name": "Bluebear",
		"gameSeries": "Animal Crossing",
		"image": "https://raw.githubusercontent.com/8bitDream/AmiiboAPI/master/images/icon_027d0001-00630502.png",
		"tail": "00630502"
	},
	"next": "00150002.html",
	"prev": "03070502.html",
	"list": {
		"00200002": "Dark Pit",
		"00fc0502": "Chops",
		"014f0502": "Buck",
		"01880502": "Peaches",
		"028e0e02": "Donkey Kong - Tennis",
		"029d0e02": "Bowser Jr. - Tennis",
		"02f80502": "Jacob",
		"03140502": "Dobie",
		"04271902": "Romin Kirishima",
		"04ac1d02": "Jamie"
	}
}
