{
	"amiibo": {
		"amiiboSeries": "Animal Crossing",
		"character": "Monique",
		"name": "Monique",
		"gameSeries": "Animal Crossing",
		"image": "https://raw.githubusercontent.com/N3evin/AmiiboAPI/master/images/icon_02680001-007d0502.png",
		"tail": "007d0502"
	},
	"next": "02ee0502.html",
	"prev": "02a40e02.html",
	"list": {
		"00250002": "Greninja",
		"007b0502": "Bangle",
		"008b0502": "Lionel",
		"01840502": "Mallary",
		"018b0502": "Boone",
		"035c0902": "Bokoblin",
		"038d0002": "Piranha Plant",
		"039bff02": "Mario - Power Up Band",
		"04131302": "E.M.M.I.",
		"042d1802": "Malzeno"
	}
}
