{
	"amiibo": {
		"amiiboSeries": "Animal Crossing",
		"character": "Copper",
		"name": "Copper",
		"gameSeries": "Animal Crossing",
		"image": "https://raw.githubusercontent.com/N3evin/AmiiboAPI/master/images/icon_019d0001-00ac0502.png",
		"tail": "00ac0502"
	},
	"next": "03060502.html",
	"prev": "02e20f02.html",
	"list": {
		"00bc0502": "Tia",
		"00c10502": "Coach",
		"010d0502": "Blathers",
		"01720502": "Katrina",
		"017e0502": "Redd - Shirt",
		"02e40f02": "Rathian and Cheval",
		"03120502": "Snooty",
		"036b0402": "Inkling Squid - Neon Purple",
		"03be0502": "Tom Nook - Coat",
		"04d11d02": "Guile"
	}
}
