{
	"amiibo": {
		"amiiboSeries": "Animal Crossing",
		"character": "Tommy",
		"name": "Tommy - Uniform",
		"gameSeries": "Animal Crossing",
		"image": "https://raw.githubusercontent.com/N3evin/AmiiboAPI/master/images/icon_01860101-00af0502.png",
		"tail": "00af0502"
	},
	"next": "038e0402.html",
	"prev": "03530902.html",
	"list": {
		"00120002": "Captain Falcon",
		"00490502": "Resetti",
		"006d0502": "Marcie",
		"011c0502": "Jingle",
		"016b0502": "Soleil",
		"02580002": "Mega Man - Gold Edition",
		"03040502": "Louie",
		"035b0902": "Revali",
		"03b50502": "Daisy Mae",
		"03c00502": "Sherb"
	}
}
