{
	"amiibo": {
		"amiiboSeries": "Animal Crossing",
		"character": "Leila",
		"name": "Leila",
		"gameSeries": "Animal Crossing",
		"image": "https://raw.githubusercontent.com/N3evin/AmiiboAPI/master/images/icon_01980001-00b10502.png",
		"tail": "00b10502"
	},
	"next": "041e0002.html",
	"prev": "03d00502.html",
	"list": {
		"004d0502": "Pascal",
		"00860502": "Flurry",
		"00a20502": "Peanut",
		"00a70502": "Walker",
		"00bd0502": "Lucha",
		"01720502": "Katrina",
		"029c0e02": "Bowser Jr. - Baseball",
		"041d0002": "Min Min",
		"04230002": "Alex",
		"04291902": "Nail Saionji"
	}
}
