{
	"amiibo": {
		"amiiboSeries": "Animal Crossing",
		"character": "Harry",
		"name": "Harry",
		"gameSeries": "Animal Crossing",
		"image": "https://raw.githubusercontent.com/N3evin/AmiiboAPI/master/images/icon_03980001-00bf0502.png",
		"tail": "00bf0502"
	},
	"next": "00660502.html",
	"prev": "04f01d02.html",
	"list": {
		"001b0002": "Ganondorf",
		"00540502": "Lottie",
		"01150502": "Cyrus",
		"01500502": "Bree",
		"01780502": "Resetti - Without Hat",
		"02b90e02": "Metal Mario - Soccer",
		"035d0302": "Poochy",
		"041b0402": "Octoling - Blue",
		"04421c02": "Yoshi - My Mario Wooden Blocks",
		"04c01d02": "Akuma"
	}
}
