{
	"amiibo": {
		"amiiboSeries": "Animal Crossing",
		"character": "Alice",
		"name": "Alice",
		"gameSeries": "Animal Crossing",
		"image": "https://raw.githubusercontent.com/N3evin/AmiiboAPI/master/images/icon_03bd0001-00f90502.png",
		"tail": "00f90502"
	},
	"next": "02630102.html",
	"prev": "03961702.html",
	"list": {
		"00540502": "Lottie",
		"00ac0502": "Copper",
		"01880502": "Peaches",
		"027e0e02": "Yoshi - Baseball",
		"02ae0e02": "Baby Luigi - Horse Racing",
		"03730102": "Bowser - Wedding",
		"037f0002": "Ridley",
		"039dff02": "Peach - Power Up Band",
		"040c0f02": "Razewing Ratha",
		"04d61d02": "Dee Jay"
	}
}
