{
	"amiibo": {
		"amiiboSeries": "Animal Crossing",
		"character": "Chops",
		"name": "Chops",
		"gameSeries": "Animal Crossing",
		"image": "https://raw.githubusercontent.com/N3evin/AmiiboAPI/master/images/icon_04860001-00fc0502.png",
		"tail": "00fc0502"
	},
	"next": "03920a02.html",
	"prev": "04a30902.html",
	"list": {
		"001f0002": "Palutena",
		"00360102": "Peach",
		"003e0402": "Inkling Girl",
		"00420302": "Pink Yarn Yoshi",
		"00660502": "Deli",
		"006e0502": "Puck",
		"00870502": "Clyde",
		"00d90502": "Coco",
		"01290502": "Velma",
		"03a70102": "Peach - Cat"
	}
}
