{
	"amiibo": {
		"amiiboSeries": "Animal Crossing",
		"character": "Charlise",
		"name": "Charlise",
		"gameSeries": "Animal Crossing",
		"image": "https://raw.githubusercontent.com/N3evin/AmiiboAPI/master/images/icon_02200001-00fd0502.png",
		"tail": "00fd0502"
	},
	"next": "03100502.html",
	"prev": "01560502.html",
	"list": {
		"000c0002": "Luigi",
		"00310002": "Mega Man",
		"017f0502": "Zipper",
		"025a0002": "Corrin",
		"027a0e02": "Daisy - Tennis",
		"02f10502": "Boris",
		"030d0502": "Cashmere",
		"03ab0502": "Orville",
		"04190902": "Zelda - Tears of the Kingdom",
		"04c91e03": "Bandana Waddle Dee"
	}
}
