{
	"amiibo": {
		"amiiboSeries": "Animal Crossing",
		"character": "Mabel",
		"name": "Mabel",
		"gameSeries": "Animal Crossing",
		"image": "https://raw.githubusercontent.com/N3evin/AmiiboAPI/master/images/icon_01880001-01120502.png",
		"tail": "01120502"
	},
	"next": "04150402.html",
	"prev": "01650502.html",
	"list": {
		"00540502": "Lottie",
		"00ed0502": "Ruby",
		"01410502": "Greta",
		"02440502": "Lottie",
		"03080502": "Boots",
		"038a0002": "Snake",
		"03d50502": "Azalea",
		"04350402": "Big Man",
		"04ed1d02": "Sagat",
		"04f01d02": "Ingrid"
	}
}
