{
	"amiibo": {
		"amiiboSeries": "Animal Crossing",
		"character": "Buck",
		"name": "Buck",
		"gameSeries": "Animal Crossing",
		"image": "https://raw.githubusercontent.com/8bitDream/AmiiboAPI/master/images/icon_03a40001-014f0502.png",
		"tail": "014f0502"
	},
	"next": "01320502.html",
	"prev": "035f1102.html",
	"list": {
		"001c0002": "Falco",
		"00d40502": "Carmen",
		"01240502": "Ken",
		"019a0502": "Anabelle",
		"025f0402": "Inkling Girl - Lime Green",
		"040f1802": "Magnamalo",
		"04291902": "Nail Saionji",
		"043f1c02": "Mario - My Mario Wooden Blocks",
		"04af1d02": "Kimberly",
		"04ba1d02": "Zangief"
	}
}
