{
	"amiibo": {
		"amiiboSeries": "Animal Crossing",
		"character": "Chadder",
		"name": "Chadder",
		"gameSeries": "Animal Crossing",
		"image": "https://raw.githubusercontent.com/N3evin/AmiiboAPI/master/images/icon_041e0001-015f0502.png",
		"tail": "015f0502"
	},
	"next": "03690402.html",
	"prev": "01440502.html",
	"list": {
		"000b0002": "Marth",
		"007d0502": "Monique",
		"008e0502": "Amelia",
		"00a00502": "Bertha",
		"02690e02": "Mario - Soccer",
		"02980e02": "Bowser - Tennis",
		"029d0e02": "Bowser Jr. - Tennis",
		"02b40e02": "Rosalina - Soccer",
		"03060502": "Admiral",
		"03630002": "Corrin - Player 2"
	}
}
