{
	"amiibo": {
		"amiiboSeries": "Animal Crossing",
		"character": "Maple",
		"name": "Maple",
		"gameSeries": "Animal Crossing",
		"image": "https://raw.githubusercontent.com/N3evin/AmiiboAPI/master/images/icon_027e0001-01690502.png",
		"tail": "01690502"
	},
	"next": "00190002.html",
	"prev": "03a90502.html",
	"list": {
		"00490502": "Resetti",
		"00ad0502": "Booker",
		"00f40502": "Flip",
		"02810e02": "Yoshi - Horse Racing",
		"02840e02": "Wario - Tennis",
		"03701202": "Tiki",
		"03710102": "Mario - Wedding",
		"03820002": "Inkling",
		"03b30502": "C.J.",
		"04e71d02": "Ingrid"
	}
}
