{
	"amiibo": {
		"amiiboSeries": "Animal Crossing",
		"character": "Static",
		"name": "Static",
		"gameSeries": "Animal Crossing",
		"image": "https://raw.githubusercontent.com/N3evin/AmiiboAPI/master/images/icon_04e50001-01ad0502.png",
		"tail": "01ad0502"
	},
	"next": "01ab0502.html",
	"prev": "00120002.html",
	"list": {
		"00640502": "Bill",
		"009a0502": "Bunnie",
		"009f0502": "Henry",
		"00fa0502": "Camofrog",
		"01210502": "Miranda",
		"01820502": "Pinky",
		"023a0702": "Hammer Slam Bowser",
		"02850e02": "Wario - Golf",
		"02990e02": "Bowser - Golf",
		"04da1d02": "Zangief"
	}
}
