{
	"amiibo": {
		"amiiboSeries": "Animal Crossing",
		"character": "Grizzly",
		"name": "Grizzly",
		"gameSeries": "Animal Crossing",
		"image": "https://raw.githubusercontent.com/N3evin/AmiiboAPI/master/images/icon_021d0001-01cd0502.png",
		"tail": "01cd0502"
	},
	"next": "00440502.html",
	"prev": "03bc0502.html",
	"list": {
		"001c0002": "Falco",
		"00740502": "Bonbon",
		"01220502": "Del",
		"013e0502": "Chester",
		"015e0502": "Frank",
		"025d0402": "Callie",
		"04c01d02": "Akuma",
		"04d41d02": "Dhalsim",
		"04de1d02": "A.K.I",
		"04e81d02": "Terry"
	}
}
