{
	"amiibo": {
		"amiiboSeries": "Legend Of Zelda",
		"character": "Midna",
		"name": "Midna \u0026 Wolf Link",
		"gameSeries": "The Legend of Zelda",
		"image": "https://raw.githubusercontent.com/N3evin/AmiiboAPI/master/images/icon_01030000-024f0902.png",
		"tail": "024f0902"
	},
	"next": "000c0002.html",
	"prev": "02f40502.html",
	"list": {
		"006a0502": "Jitters",
		"00930502": "Eugene",
		"01690502": "Maple",
		"017a0502": "Lottie - Black Skirt And Bow",
		"01b40502": "Sylvia",
		"02420502": "Tom Nook",
		"02f50502": "Rex",
		"03750d02": "Detective Pikachu",
		"0431ff02": "Donkey Kong - Power Up Band",
		"04b01d02": "Chun-Li"
	}
}
