{
	"amiibo": {
		"amiiboSeries": "Shovel Knight",
		"character": "Shovel Knight",
		"name": "Shovel Knight",
		"gameSeries": "Shovel Knight",
		"image": "https://raw.githubusercontent.com/N3evin/AmiiboAPI/master/images/icon_35c00000-02500a02.png",
		"tail": "02500a02"
	},
	"next": "03911602.html",
	"prev": "00f20502.html",
	"list": {
		"00c60502": "Pate",
		"00e60502": "Ed",
		"011d0502": "Lily",
		"023d0002": "Mewtwo",
		"02c10e02": "Pink Gold Peach - Golf",
		"02fc0502": "Bitty",
		"03870002": "Pokemon Trainer",
		"041a0902": "Ganondorf - Tears of the Kingdom",
		"042a1902": "Asana Mutsuba",
		"042f1a02": "Donkey Kong \u0026 Pauline"
	}
}
