{
	"amiibo": {
		"amiiboSeries": "Super Mario Bros.",
		"character": "Boo",
		"name": "Boo",
		"gameSeries": "Super Mario",
		"image": "https://raw.githubusercontent.com/8bitDream/AmiiboAPI/master/images/icon_00170000-02680102.png",
		"tail": "02680102"
	},
	"next": "018e0502.html",
	"prev": "02f80502.html",
	"list": {
		"00c30502": "Tom",
		"00f70502": "Pecan",
		"010d0502": "Blathers",
		"01820502": "Pinky",
		"018c0502": "Broffina",
		"01960502": "Frita",
		"01c10502": "Lobo",
		"02580002": "Mega Man - Gold Edition",
		"03800002": "Dark Samus",
		"03b10502": "Label"
	}
}
