{
	"amiibo": {
		"amiiboSeries": "Mario Sports Superstars",
		"character": "Baby Luigi",
		"name": "Baby Luigi - Golf",
		"gameSeries": "Mario Sports Superstars",
		"image": "https://raw.githubusercontent.com/N3evin/AmiiboAPI/master/images/icon_09cd0401-02ad0e02.png",
		"tail": "02ad0e02"
	},
	"next": "02860e02.html",
	"prev": "026c0e02.html",
	"list": {
		"00820502": "Mint",
		"015f0502": "Chadder",
		"01bc0502": "Sydney",
		"027b0e02": "Daisy - Golf",
		"02b50e02": "Rosalina - Baseball",
		"02e10f02": "One-Eyed Rathalos and Rider - Male",
		"04131302": "E.M.M.I.",
		"04b71d02": "Manon",
		"04b81d02": "Marisa",
		"04d01d02": "Chun-Li"
	}
}
