{
	"amiibo": {
		"amiiboSeries": "Mario Sports Superstars",
		"character": "Rosalina",
		"name": "Rosalina - Soccer",
		"gameSeries": "Mario Sports Superstars",
		"image": "https://raw.githubusercontent.com/N3evin/AmiiboAPI/master/images/icon_09cf0101-02b40e02.png",
		"tail": "02b40e02"
	},
	"next": "034e0902.html",
	"prev": "00000002.html",
	"list": {
		"003f0402": "Inkling Boy",
		"00790502": "Deena",
		"00c00502": "Gwen",
		"00fe0502": "Vic",
		"01650502": "Caroline",
		"02600402": "Inkling Boy - Purple",
		"02660102": "Daisy",
		"02940e02": "Diddy Kong - Golf",
		"037c0002": "Young Link",
		"04da1d02": "Zangief"
	}
}
