{
	"amiibo": {
		"amiiboSeries": "Animal Crossing",
		"character": "Wade",
		"name": "Wade",
		"gameSeries": "Animal Crossing",
		"image": "https://raw.githubusercontent.com/N3evin/AmiiboAPI/master/images/icon_04680001-02f20502.png",
		"tail": "02f20502"
	},
	"next": "01d60502.html",
	"prev": "02fe0502.html",
	"list": {
		"00480502": "Kapp'n",
		"00970502": "Benjamin",
		"01250502": "Mitzi",
		"01b80502": "Pompom",
		"01c30502": "Margie",
		"029f0e02": "Bowser Jr. - Horse Racing",
		"04261902": "Gakuto Sōgetsu",
		"04ac1d02": "Jamie",
		"04de1d02": "A.K.I",
		"04f11d02": "Terry"
	}
}
