{
	"amiibo": {
		"amiiboSeries": "Animal Crossing",
		"character": "Rilla",
		"name": "Rilla",
		"gameSeries": "Animal Crossing",
		"image": "https://raw.githubusercontent.com/N3evin/AmiiboAPI/master/images/icon_03740101-03190502.png",
		"tail": "03190502"
	},
	"next": "00080002.html",
	"prev": "041e0002.html",
	"list": {
		"00570502": "Curt",
		"00810502": "T-Bone",
		"00c20502": "Kitt",
		"01130502": "Leif",
		"027c0e02": "Daisy - Horse Racing",
		"02940e02": "Diddy Kong - Golf",
		"031a0502": "Marty",
		"04330402": "Shiver",
		"04bd1d02": "Rashid",
		"04e11d02": "M. Bison"
	}
}
