{
	"amiibo": {
		"amiiboSeries": "Legend Of Zelda",
		"character": "Link",
		"name": "Link - Majora's Mask",
		"gameSeries": "The Legend of Zelda",
		"image": "https://raw.githubusercontent.com/N3evin/AmiiboAPI/master/images/icon_01000000-034c0902.png",
		"tail": "034c0902"
	},
	"next": "017a0502.html",
	"prev": "03cb0502.html",
	"list": {
		"005b0502": "Kyle",
		"01280502": "Cousteau",
		"013e0502": "Chester",
		"01430502": "Diva",
		"02530002": "Ryu",
		"02be0e02": "Pink Gold Peach - Soccer",
		"036f1202": "Chrom",
		"037f0002": "Ridley",
		"041b0402": "Octoling - Blue",
		"04220002": "Steve"
	}
}
