{
	"amiibo": {
		"amiiboSeries": "Power Pros",
		"character": "Ikari",
		"name": "Ikari",
		"gameSeries": "Power Pros",
		"image": "https://raw.githubusercontent.com/N3evin/AmiiboAPI/master/images/icon_38010001-03941702.png",
		"tail": "03941702"
	},
	"next": "03500902.html",
	"prev": "01930502.html",
	"list": {
		"001c0002": "Falco",
		"00330002": "R.O.B. - NES",
		"00680502": "Kabuki",
		"00770502": "Poppy",
		"009f0502": "Henry",
		"01000502": "Drift",
		"01660502": "Sparro",
		"028d0e02": "Donkey Kong - Baseball",
		"02940e02": "Diddy Kong - Golf",
		"039fff02": "Yoshi - Power Up Band"
	}
}
