{
	"amiibo": {
		"amiiboSeries": "Animal Crossing",
		"character": "Reneigh",
		"name": "Reneigh",
		"gameSeries": "Animal Crossing",
		"image": "https://raw.githubusercontent.com/N3evin/AmiiboAPI/master/images/icon_0a100001-03c70502.png",
		"tail": "03c70502"
	},
	"next": "00600502.html",
	"prev": "01250502.html",
	"list": {
		"00980502": "Pancetti",
		"01170502": "Timmy - Full Apron",
		"01590502": "Dora",
		"015b0502": "Victoria",
		"02380602": "8-Bit Mario Classic Color",
		"02740e02": "Peach - Baseball",
		"02810e02": "Yoshi - Horse Racing",
		"03040502": "Louie",
		"037b0002": "King K. Rool",
		"03b90502": "Gulliver"
	}
}
